githubproj/__init__.py
githubproj/client.py
githubproj/issues.py
githubproj/labels.py
githubproj/project.py
githubproj/schema.py
githubproj-0.3.0.dist-info/licenses/LICENSE
githubproj-0.3.0.dist-info/METADATA
githubproj-0.3.0.dist-info/WHEEL
githubproj-0.3.0.dist-info/top_level.txt
githubproj-0.3.0.dist-info/RECORD
