Metadata-Version: 2.4
Name: githubproj
Version: 0.3.0
Summary: CRUD toolkit for GitHub Projects (v2) via GraphQL API
Author-email: Aureuma AI <x@aureuma.ai>
License-Expression: MIT
Project-URL: Homepage, https://github.com/Aureuma/GitHubProj
Project-URL: Bug Tracker, https://github.com/Aureuma/GitHubProj/issues
Keywords: github,projects,graphql,api,automation
Classifier: Intended Audience :: Developers
Classifier: Intended Audience :: System Administrators
Classifier: Programming Language :: Python :: 3
Classifier: Programming Language :: Python :: 3.9
Classifier: Programming Language :: Python :: 3.10
Classifier: Programming Language :: Python :: 3.11
Classifier: Programming Language :: Python :: 3.12
Classifier: Programming Language :: Python :: 3.13
Classifier: Programming Language :: Python :: 3.14
Classifier: Operating System :: OS Independent
Classifier: Topic :: Software Development :: Libraries :: Python Modules
Requires-Python: >=3.9
License-File: LICENSE
Requires-Dist: toml; python_version < "3.11"
Provides-Extra: dev
Requires-Dist: ruff; extra == "dev"
Requires-Dist: pytest; extra == "dev"
Requires-Dist: pytest-mock; extra == "dev"
Requires-Dist: build; extra == "dev"
Requires-Dist: twine; extra == "dev"
Dynamic: license-file
